dtpattern/__init__.py
dtpattern/cli.py
dtpattern/dtpattern1.py
dtpattern/dtpattern2.py
dtpattern/suffix_tree.py
dtpattern/suffix_tree_lists.py
dtpattern/timer.py
dtpattern/utils.py
dtpattern/value_pattern_detection.py
dtpattern/alignment/__init__.py
dtpattern/alignment/alignment_cls.py
dtpattern/alignment/alignment_list.py
dtpattern/alignment/merge.py
dtpattern/alignment/pattern_cls.py
dtpattern/alignment/utils.py
dtpattern/services/__init__.py
dtpattern/services/cli_demo.py
dtpattern/services/cli_dtpattern.py
dtpattern/services/cli_dtpattern2.py
dtpattern/services/cli_dtpattern_new.py
dtpattern/services/cli_ucs.py
dtpattern/unicode_translate/__init__.py
dtpattern/unicode_translate/category.py
dtpattern/unicode_translate/pattern_detection_print.py
dtpattern/unicode_translate/translate.py
dtpattern/unicode_translate/uc_models.py
dtpattern/unicode_translate/unicode_categories.py
dtpattern-0.7.dist-info/METADATA
dtpattern-0.7.dist-info/RECORD
dtpattern-0.7.dist-info/WHEEL
dtpattern-0.7.dist-info/entry_points.txt
dtpattern-0.7.dist-info/top_level.txt
