Metadata-Version: 2.1
Name: dtpattern
Version: 0.7
Summary: Add a short description here!
Home-page: http://...
Author: jumbrich
Author-email: jueumb@gmail.com
License: mit
Platform: any
Classifier: Development Status :: 4 - Beta
Classifier: Programming Language :: Python
Requires-Dist: click
Requires-Dist: multipledispatch
